Workbook

Sheet Assumptions
A1: CENCORI — CAP TABLE
A2: Delaware C-Corp · Stripe Atlas · Definitive Founder Equity
A4: COMPANY DETAILS
A5: Incorporation | B5: Delaware C-Corp (Stripe Atlas)
A6: Authorized Shares | B6: 10000000
A7: Pre-Seed Valuation | B7: 3000000
A8: Seed Valuation (Pre-Money) | B8: 18000000
A9: Seed Raise Amount | B9: 3000000
A10: Post-Money Valuation (Seed) | B10: =B8+B9 -> 21000000
A12: SHARE PRICING
A13: Price/Share (Pre-Seed) | B13: =B7/B6 -> 0.3
A14: Price/Share (Seed) | B14: =B8/B6 -> 1.8
A15: Step-Up Multiple | B15: =B14/B13 -> 6
A17: HOURLY RATES (for sweat equity reference)
A18: Founder Rate | B18: 125
A19: Contributor Rate | B19: 75

Sheet Hours Log
A1: SWEAT EQUITY — HOURS LOG
A2: Reference only — equity allocation was decided by founders, not strictly derived from hours.
A4: Name | B4: Role | C4: Rate Tier | D4: Start Date | E4: Days Active | F4: Avg Hrs/Day | G4: Total Hours | H4: Cash Equivalent
A5: Bola Roy Banjo | B5: CEO & Co-Founder | C5: Founder | D5: Nov 1, 2025 | E5: 150 | F5: 15 | G5: =E5*F5 -> 2250 | H5: =G5*Assumptions!B18 -> 281250
A6: Oreofe Daniel | B6: COO & Co-Founder | C6: Founder | D6: Dec 15, 2025 | E6: 105 | F6: 3 | G6: =E6*F6 -> 315 | H6: =G6*Assumptions!B18 -> 39375
A7: Ladipo Samuel | B7: CTO & Co-Founder | C7: Founder | D7: Various | E7: 14 | F7: 5.7 | G7: =E7*F7 -> 79.8 | H7: =G7*Assumptions!B18 -> 9975
A8: Rosemary | B8: Frontend Developer | C8: Contributor | D8: Various | E8: 30 | F8: 3 | G8: =E8*F8 -> 90 | H8: =G8*Assumptions!B19 -> 6750
A9: TOTAL | G9: =SUM(G5:G8) -> 2734.8 | H9: =SUM(H5:H8) -> 337350

Sheet Cap Table
A1: CENCORI — DEFINITIVE CAP TABLE (PRE-SEED)
A2: Founder-agreed equity split · 10,000,000 authorized shares · $0.30/share pre-seed
A4: Shareholder | B4: Ownership % | C4: Shares | D4: Value (Pre-Seed) | E4: Value (at Seed $18M) | F4: Notes
A5: Bola Roy Banjo | B5: 0.58 | C5: =B5*Assumptions!B6 -> 5800000 | D5: =B5*Assumptions!B7 -> 1740000 | E5: =B5*Assumptions!B8 -> 10440000 | F5: CEO & Co-Founder · Full-time since Nov 2025 · Vision + IP holder
A6: Oreofe Daniel | B6: 0.2 | C6: =B6*Assumptions!B6 -> 2000000 | D6: =B6*Assumptions!B7 -> 600000 | E6: =B6*Assumptions!B8 -> 3600000 | F6: COO & Co-Founder · Consistent contribution alongside day job
A7: Ladipo Samuel | B7: 0.2 | C7: =B7*Assumptions!B6 -> 2000000 | D7: =B7*Assumptions!B7 -> 600000 | E7: =B7*Assumptions!B8 -> 3600000 | F7: CTO & Co-Founder · Technical leadership role
A8: Rosemary | B8: 0.02 | C8: =B8*Assumptions!B6 -> 200000 | D8: =B8*Assumptions!B7 -> 60000 | E8: =B8*Assumptions!B8 -> 360000 | F8: Frontend Developer · 1 month part-time contribution
A9: Mary Ima Owen | B9: 0 | C9: =B9*Assumptions!B6 -> 0 | D9: =B9*Assumptions!B7 -> 0 | E9: =B9*Assumptions!B8 -> 0 | F9: Chief of Staff & Head of Capital · Not yet allocated
A10: ESOP (Reserved) | B10: 0 | C10: =B10*Assumptions!B6 -> 0 | D10: =B10*Assumptions!B7 -> 0 | E10: =B10*Assumptions!B8 -> 0 | F10: Employee option pool · To be set before seed round
A11: Unallocated | B11: =1-SUM(B5:B10) -> 0 | C11: =B11*Assumptions!B6 -> 0 | D11: =B11*Assumptions!B7 -> 0 | E11: =B11*Assumptions!B8 -> 0 | F11: Buffer for Mary, ESOP, advisors
A12: TOTAL | B12: =SUM(B5:B11) -> 1 | C12: =SUM(C5:C11) -> 10000000 | D12: =SUM(D5:D11) -> 3000000 | E12: =SUM(E5:E11) -> 18000000
A14: KEY DECISIONS PENDING
A15: 1. Mary Ima Owen's equity allocation — to be decided based on scope of Chief of Staff & Head of Capital role
A16: 2. ESOP pool size — standard is 10-15% pre-seed, but can be set closer to seed round
A17: 3. Vesting schedules — recommended 4-year vest with 1-year cliff for all co-founders except CEO
A18: 4. The 18% currently unallocated can be distributed across Mary, ESOP, and future advisors

Sheet Post-Seed Dilution
A1: POST-SEED DILUTION MODEL
A2: Raising $3M at $18M pre-money = $21M post-money · Investors get 14.3%
A4: SEED ROUND MECHANICS
A5: Investor Ownership | B5: =Assumptions!B9/Assumptions!B10 -> 0.14285714
A6: Dilution Factor | B6: =1-B5 -> 0.85714286
A7: New Shares Issued to Investors | B7: =Assumptions!B9/Assumptions!B14 -> 1666666.7
A9: Shareholder | B9: Pre-Seed % | C9: Post-Seed % | D9: Post-Seed Shares | E9: Post-Seed Value ($21M)
A10: Bola Roy Banjo | B10: ='Cap Table'!B5 -> 0.58 | C10: =B10*$B$6 -> 0.49714286 | D10: ='Cap Table'!C5 -> 5800000 | E10: =C10*Assumptions!B10 -> 10440000
A11: Oreofe Daniel | B11: ='Cap Table'!B6 -> 0.2 | C11: =B11*$B$6 -> 0.17142857 | D11: ='Cap Table'!C6 -> 2000000 | E11: =C11*Assumptions!B10 -> 3600000
A12: Ladipo Samuel | B12: ='Cap Table'!B7 -> 0.2 | C12: =B12*$B$6 -> 0.17142857 | D12: ='Cap Table'!C7 -> 2000000 | E12: =C12*Assumptions!B10 -> 3600000
A13: Rosemary | B13: ='Cap Table'!B8 -> 0.02 | C13: =B13*$B$6 -> 0.017142857 | D13: ='Cap Table'!C8 -> 200000 | E13: =C13*Assumptions!B10 -> 360000
A14: Mary Ima Owen | B14: ='Cap Table'!B9 -> 0 | C14: =B14*$B$6 -> 0 | D14: ='Cap Table'!C9 -> 0 | E14: =C14*Assumptions!B10 -> 0
A15: ESOP (Reserved) | B15: ='Cap Table'!B10 -> 0 | C15: =B15*$B$6 -> 0 | D15: ='Cap Table'!C10 -> 0 | E15: =C15*Assumptions!B10 -> 0
A16: Unallocated | B16: ='Cap Table'!B11 -> 0 | C16: =B16*$B$6 -> 0 | D16: ='Cap Table'!C11 -> 0 | E16: =C16*Assumptions!B10 -> 0
A17: Seed Investors | B17: - | C17: =$B$5 -> 0.14285714 | D17: =$B$7 -> 1666666.7 | E17: =C17*Assumptions!B10 -> 3000000
A18: TOTAL | C18: =SUM(C10:C17) -> 1
A20: FOUNDER EQUITY VALUE AT SEED
A21: Bola Roy Banjo (58% pre-seed) | B21: Post-dilution value: | C21: =E10 -> 10440000
A22: Oreofe Daniel (20% pre-seed) | B22: Post-dilution value: | C22: =E11 -> 3600000
A23: Ladipo Samuel (20% pre-seed) | B23: Post-dilution value: | C23: =E12 -> 3600000
